inference/__init__.py
inference/setup.py
inference/zen/__init__.py
inference/zen/index.py
inference/zen/inference_pb2.py
inference/zen/inference_pb2_grpc.py
inference/zen/model_pb2.py
inference/zen/model_pb2_grpc.py
inference/zen/setup.py
inference/zen/task_pb2.py
inference/zen/task_pb2_grpc.py
zen/__init__.py
zen/index.py
zen/inference_pb2.py
zen/inference_pb2_grpc.py
zen/model_pb2.py
zen/model_pb2_grpc.py
zen/task_pb2.py
zen/task_pb2_grpc.py
zenai/__init__.py
zenai/index.py
zenai/inference_pb2.py
zenai/inference_pb2_grpc.py
zenai/model_pb2.py
zenai/model_pb2_grpc.py
zenai/task_pb2.py
zenai/task_pb2_grpc.py
zenai-0.0.6.dist-info/METADATA
zenai-0.0.6.dist-info/WHEEL
zenai-0.0.6.dist-info/top_level.txt
zenai-0.0.6.dist-info/RECORD
