Metadata-Version: 2.1
Name: zenai
Version: 0.0.6
Requires-Dist: google
Requires-Dist: protobuf
Requires-Dist: grpcio
